{"object":"company","name":"Nem Nome Tem","phone_number":"11984805184","site_url":"http://www.nemnometem.me","statement_descriptor":null,"full_name":"Nem Nome Tem","cnpj":"54346352000122","address":{"street":"Rua Correia de Lemos","complementary":"","street_number":"390","neighborhood":"Chácara Inglesa","city":"São Paulo","state":"SP","zipcode":"04140-000"},"managing_partner":{"name":"Pedro","cpf":"39326595897","phone_number":"11912345678"},"account_manager":{"name":"Pedro ","cpf":"39326595897","email":"pedrinho@pagar.com"},"anticipation_config":{"max_anticipation_days":0,"minimum_delay":360,"config_default_recipient":false,"config_anticipation_params":false},"status":"active","seller_id":null,"id":"123456789545","date_created":"2017-06-07T18:02:45.458Z","preferences":{},"branding":{"primary_color":null,"logo":"https://d1fzuw5mzeho8x.cloudfront.net/companies/59383fc59f43ef414791cdb4/branding/logo_1522678066546.png"},"default_recipient_id":{"live":"re_cj123456","test":"re_cj123456"},"events":{"transaction":{"transaction_status_changed":{"postback":true}},"subscription":{"subscription_status_changed":{"postback":true},"transaction_created":{"postback":false}},"recipient":{"recipient_status_changed":{"postback":true}}},"transactions":{"enforce_zipcode_existence":false},"pricing":{"gateway":{"live":{"transaction_cost":{"credit_card":50,"debit_card":50,"boleto":380},"transaction_spread":{"credit_card":0,"debit_card":1.5,"boleto":0},"minimum_monthly_payment":0,"antifraud_cost":[{"name":"konduto","cost":70},{"name":"siftscience","cost":0}]}},"psp":{"live":{"anticipation":3.14,"mdrs":[]}},"transfers":{"credito_em_conta":0,"ted":367,"doc":367}},"boletos":{"instrucoes":"Sr. Caixa, favor não aceitar pagamento após o vencimento.","days_to_add_in_expiration_date":3},"notifications":{"live":[],"test":[]},"api_version":{"live":"2017-08-28","test":"2017-08-28"},"capabilities":{"allow_payment_link":false,"allow_chatbot":true},"users":[{"object":"user","id":"59383fc59f43ef414791cdba","email":"pe@mao.braco","name":"Pagar.me","permission":"admin","date_created":"2017-06-07T18:02:45.536Z"},{"object":"user","id":"5a6762b326596fdc60374bdd","email":"escrita@gmail.com","name":"Leitura e Escrita","permission":"read_write","date_created":"2018-01-23T16:28:35.609Z"},{"object":"user","id":"5a67847326596fdc60374be7","email":"leitura@gmail.com","name":"Geisson Conta teste PEDRO","permission":"admin","date_created":"2018-01-23T18:52:35.659Z"},{"object":"user","id":"5a95c8388e18fee52e6aad5e","email":"vitor.rock12@gmail.com","name":"Vitor Silva Lima","permission":"admin","date_created":"2018-02-27T21:06:00.669Z"},{"object":"user","id":"5a9fe0e7d82eb3f448a398e6","email":"leituraamaescrita@gmail.com","name":"Dannilo Neiva de Carvalho","permission":"read_write","date_created":"2018-03-07T12:53:59.029Z"}],"api_key":{"test":"ak_test_123456","live":"ak_live_12345"},"encryption_key":{"test":"ek_test_12345","live":"ek_live_12345"},"subscriptions":{"payment_deadline":5,"email_customers":true,"charge_attempts":4,"charges_interval_in_days":3,"cancel_after_failed_charges":false,"customer_can_cancel_subscription":true},"transaction_cost":{"credit_card":50,"debit_card":50,"boleto":380},"transaction_spread":{"credit_card":0,"debit_card":1.5,"boleto":0},"antifraud":{"test":{"fraud_covered":false,"providers":[{"id":"59383fc59f43ef414791cdb9","enabled":true,"name":"development","last_enabled_change":"2017-06-07T18:02:45.469Z"}],"enabled":true,"last_enabled_change":"2017-07-31T21:40:35.210Z","rule":"development.score <= 95.0 || development.status == 'failed'"},"live":{"fraud_covered":false,"providers":[{"id":"59383fc59f43ef414791cdb8","enabled":false,"name":"b","last_enabled_change":"2017-06-07T18:02:45.469Z"},{"id":"5a2fdad81ea22a3d2f2d4552","enabled":true,"name":"a","last_enabled_change":"2017-12-12T13:34:16.214Z"},{"id":"5ac662c38072856529f7181a","enabled":true,"name":"c","last_enabled_change":"2018-04-05T17:54:11.503Z"}],"enabled":true,"last_enabled_change":"2017-12-07T21:27:41.491Z","rule":"( Math.random() < 0.01 ? ({ status: (c.score <= 0.3 ? 'approved' : 'refused'), decision_maker: 'c' }) : ({ status: a.status, decision_maker: 'a' }))"}},"customer_manager":{"id":"56c4a3a41144ea1a2fcbc1234","name":"Abc","email":"abc@pagar.com"}}
